nbktools/__init__.py
nbktools/src/__init__.py
nbktools/src/nbktools.py
nbktools-0.0.18.dist-info/LICENSE
nbktools-0.0.18.dist-info/METADATA
nbktools-0.0.18.dist-info/WHEEL
nbktools-0.0.18.dist-info/top_level.txt
nbktools-0.0.18.dist-info/RECORD
