Metadata-Version: 2.1
Name: nbktools
Version: 0.0.18
Summary: TBC 
Home-page: https://github.com/bouz1/PypiContributions/tree/main/notebook_tools
Author: Abb BOZZ
Author-email: bozzabb1@gmail.com
License: MIT
Platform: UNKNOWN
Classifier: License :: OSI Approved :: MIT License
Classifier: Programming Language :: Python :: 3.10
Classifier: Operating System :: OS Independent
Requires-Python: >=3.1
License-File: LICENSE
Provides-Extra: dev
Requires-Dist: os ; extra == 'dev'
